printutilites_common/calcer.py
printutilites-1.0.1.dist-info/LICENCE
printutilites-1.0.1.dist-info/METADATA
printutilites-1.0.1.dist-info/WHEEL
printutilites-1.0.1.dist-info/top_level.txt
printutilites-1.0.1.dist-info/RECORD
